LICENSE
MANIFEST.in
README.md
pyproject.toml
setup.cfg
setup.py
youtube_multi_dl/__init__.py
youtube_multi_dl/command_line.py
youtube_multi_dl/downloader.py
youtube_multi_dl.egg-info/PKG-INFO
youtube_multi_dl.egg-info/SOURCES.txt
youtube_multi_dl.egg-info/dependency_links.txt
youtube_multi_dl.egg-info/entry_points.txt
youtube_multi_dl.egg-info/requires.txt
youtube_multi_dl.egg-info/top_level.txt