Metadata-Version: 1.1
Name: youtube-multi-dl
Version: 1.3.3
Summary: Download and label albums and playlists from YouTube using youtube-dl
Home-page: https://github.com/fortana-co/youtube-multi-dl
Author: kylebebak
Author-email: kylebebak@gmail.com
License: MIT
Download-URL: https://github.com/fortana-co/youtube-multi-dl/tarball/1.3.3
Keywords: youtube youtube-dl mp3 download playlist album chapters file id3
Platform: UNKNOWN
Classifier: Intended Audience :: Developers
Classifier: License :: OSI Approved :: MIT License
Classifier: Programming Language :: Python
